transformer_tools/__init__.py
transformer_tools/callback.py
transformer_tools/mlflow_transformers_flavor.py
transformer_tools/transformers.py
transformer_tools-0.1.0.dist-info/LICENSE
transformer_tools-0.1.0.dist-info/METADATA
transformer_tools-0.1.0.dist-info/WHEEL
transformer_tools-0.1.0.dist-info/top_level.txt
transformer_tools-0.1.0.dist-info/RECORD
